{
  "name": "SetLightColor",
  "arguments": [
    {
      "name": "handle",
      "desc": "Light handle",
      "optional": false,
      "type": "number"
    },
    {
      "name": "r",
      "desc": "Red value",
      "optional": false,
      "type": "number"
    },
    {
      "name": "g",
      "desc": "Green value",
      "optional": false,
      "type": "number"
    },
    {
      "name": "b",
      "desc": "Blue value",
      "optional": false,
      "type": "number"
    }
  ],
  "returns": [],
  "examples": [
    [
      "function init()",
      "\t--Set light color to yellow",
      "\tSetLightColor(FindLight(\"main\"), 1, 1, 0)",
      "end"
    ]
  ],
  "description": [
    "This will only set the color tint of the light. Use SetLightIntensity for brightness.",
    "Setting the light color will not affect the emissive color of a parent shape."
  ]
}